moya/.DS_Store
moya/.coverage
moya/__init__.py
moya/__main__.py
moya/_version.py
moya/application.py
moya/application.pyc
moya/archive.py
moya/archive.pyc
moya/asgi.py
moya/bbcode.py
moya/bbcode.pyc
moya/browser.py
moya/build.py
moya/build.pyc
moya/compat.py
moya/compat.pyc
moya/connectivity.py
moya/connectivity.pyc
moya/console.py
moya/console.pyc
moya/consolehtml.py
moya/containers.py
moya/containers.pyc
moya/content.py
moya/content.pyc
moya/contextenum.py
moya/contextenum.pyc
moya/db.py
moya/db.pyc
moya/dbexpression.py
moya/dbexpression.pyc
moya/debugger.py
moya/debugger.pyc
moya/debugprint.py
moya/debugprint.pyc
moya/diagnose.py
moya/diagnose.pyc
moya/document.py
moya/document.pyc
moya/enum.py
moya/enum.pyc
moya/errors.py
moya/errors.pyc
moya/executor.pyc
moya/filesystems.py
moya/filesystems.pyc
moya/filter.py
moya/filter.pyc
moya/filtercontainer.py
moya/filtercontainer.pyc
moya/generickey.py
moya/generickey.pyc
moya/html.py
moya/html.pyc
moya/http.py
moya/http.pyc
moya/importer.py
moya/importer.pyc
moya/iniparse.py
moya/iniparse.pyc
moya/interface.py
moya/interface.pyc
moya/jsonrpc.py
moya/jsonrpc.pyc
moya/library.py
moya/library.pyc
moya/loggingconf.py
moya/loggingconf.pyc
moya/logic.py
moya/logic.pyc
moya/logtools.py
moya/logtools.pyc
moya/luhn.py
moya/mail.py
moya/mail.pyc
moya/markup.py
moya/markup.pyc
moya/moyaexceptions.py
moya/moyaexceptions.pyc
moya/moyajson.py
moya/moyajson.pyc
moya/moyapilot.py
moya/moyapilot.pyc
moya/multiwsgi.py
moya/multiwsgi.pyc
moya/namespaces.py
moya/namespaces.pyc
moya/package.py
moya/package.pyc
moya/parser.py
moya/parser.pyc
moya/progress.py
moya/progress.pyc
moya/pyversion.py
moya/pyversion.pyc
moya/reader.py
moya/reader.pyc
moya/render.py
moya/render.pyc
moya/request.py
moya/request.pyc
moya/response.py
moya/response.pyc
moya/run.py
moya/run.pyc
moya/scheduler.py
moya/serve.py
moya/serve.pyc
moya/service.py
moya-0.6.20.dist-info/DESCRIPTION.rst
moya-0.6.20.dist-info/METADATA
moya-0.6.20.dist-info/RECORD
moya-0.6.20.dist-info/WHEEL
moya-0.6.20.dist-info/entry_points.txt
moya-0.6.20.dist-info/metadata.json
moya-0.6.20.dist-info/top_level.txt
