Metadata-Version: 1.1
Name: moya
Version: 0.6.20
Summary: web development platform
Home-page: http://www.moyaproject.com
Author: Will McGugan
Author-email: will@willmcgugan.com
License: MIT
Platform: any
Classifier: Intended Audience :: Developers
Classifier: License :: OSI Approved :: MIT License
Classifier: Operating System :: OS Independent
Classifier: Programming Language :: Python
Classifier: Programming Language :: Python :: 2.7
Classifier: Programming Language :: Python :: 3.4
Classifier: Programming Language :: Python :: 3.5
